flowtest/__init__.py
flowtest/test_flowtest.py
flowtest-0.2.1.dist-info/LICENSE
flowtest-0.2.1.dist-info/METADATA
flowtest-0.2.1.dist-info/WHEEL
flowtest-0.2.1.dist-info/top_level.txt
flowtest-0.2.1.dist-info/RECORD
