Metadata-Version: 2.1
Name: flowtest
Version: 0.2.1
Summary: Flow-based integration test framework for python
Home-page: https://flowtest.readthedocs.io/en/latest/
Author: Klaas Mussche
Author-email: klaasmussche@gmail.com
License: UNKNOWN
Platform: UNKNOWN
Classifier: Programming Language :: Python :: 3
Classifier: License :: OSI Approved :: MIT License
Classifier: Operating System :: OS Independent
Classifier: Development Status :: 4 - Beta
Classifier: Intended Audience :: Developers
Classifier: Topic :: Software Development :: Testing
Requires-Dist: networkx
